somfy/__init__.py
somfy/connector.py
somfy/enumutils.py
somfy/messages.py
somfy/payloads.py
somfy/recognizer.py
somfy/serial.py
somfy/utils.py
python_somfy-1.2.0.dist-info/LICENSE
python_somfy-1.2.0.dist-info/METADATA
python_somfy-1.2.0.dist-info/WHEEL
python_somfy-1.2.0.dist-info/top_level.txt
python_somfy-1.2.0.dist-info/RECORD
