Metadata-Version: 2.1
Name: python-somfy
Version: 1.2.0
Summary: Python library for local control of Somfy SDN shades
Home-page: https://github.com/Cyberax/py-somfy-sdn
Author: Aleksei Besogonov
Author-email: b@alex.net
License: Apache-2.0
Project-URL: Bug Tracker, https://github.com/Cyberax/py-somfy-sdn
Platform: any
Classifier: Development Status :: 4 - Beta
Classifier: Intended Audience :: Developers
Classifier: License :: OSI Approved :: Apache Software License
Classifier: Operating System :: POSIX :: Linux
Classifier: Programming Language :: Python :: 3
Classifier: Topic :: Home Automation
Requires-Python: >=3.12
License-File: LICENSE
Requires-Dist: typing-extensions ; python_version < "3.8"
